komut/__init__.py
komut-0.1.0.dist-info/LICENSE
komut-0.1.0.dist-info/METADATA
komut-0.1.0.dist-info/WHEEL
komut-0.1.0.dist-info/top_level.txt
komut-0.1.0.dist-info/RECORD
