Metadata-Version: 2.1
Name: komut
Version: 0.1.0
Summary: A High-Magic CLI Framework
Home-page: https://github.com/alpernebbi/komut
Author: Alper Nebi Yasak
Author-email: alpernebiyasak@gmail.com
License: GPL2+
Keywords: cli command line interface
Classifier: Development Status :: 1 - Planning
Classifier: Environment :: Console
Classifier: Intended Audience :: Developers
Classifier: License :: OSI Approved :: GNU General Public License v2 or later (GPLv2+)
Classifier: Operating System :: POSIX :: Linux
Classifier: Programming Language :: Python :: 3
Classifier: Topic :: Software Development :: Libraries :: Application Frameworks
License-File: LICENSE
Requires-Dist: setuptools
